{"v":"4.8.0","meta":{"g":"LottieFiles AE 1.1.0","a":"","k":"","d":"","tc":""},"fr":30,"ip":0,"op":150,"w":500,"h":500,"nm":"3 - Weigth scale","ddd":0,"assets":[],"layers":[{"ddd":0,"ind":2,"ty":4,"nm":"Mask","parent":7,"td":1,"sr":1,"ks":{"o":{"a":0,"k":100,"ix":11},"r":{"a":0,"k":0,"ix":10},"p":{"a":0,"k":[175.25,88.795,0],"ix":2},"a":{"a":0,"k":[91.664,54.352,0],"ix":1},"s":{"a":0,"k":[100,100,100],"ix":6}},"ao":0,"shapes":[{"ty":"gr","it":[{"ind":0,"ty":"sh","ix":1,"ks":{"a":0,"k":{"i":[[73.132,-27.488999999999997],[51.491,-19.065],[48.645,-16.368],[44.873999999999995,-16.610999999999997],[40.53,-22.005000000000003],[51.832,-41.235],[22.185000000000002,-53.278999999999996],[5.469,-35.221],[3.019,-29.752],[-5.469,-32.199999999999996],[-5.469,-54.102],[-37.908,-48.728],[-42.057,-24.609],[-41.397,-18.654],[-45.828,-16.368],[-50.467999999999996,-17.332],[-61.18,-35.554],[-83.436,-17.174],[-64.068,54.102],[64.069,54.102],[91.414,-5.158]],"o":[[61.182,-35.553],[50.471,-17.332],[45.828,-16.368],[41.4,-18.654],[42.06,-24.609],[37.909,-48.727],[5.469,-54.102],[5.469,-32.199999999999996],[-3.021,-29.752],[-5.469,-35.221],[-22.184,-53.278],[-51.829,-41.235],[-40.527,-22.005000000000003],[-44.870999999999995,-16.610999999999997],[-48.643,-16.368],[-51.488,-19.065],[-73.129,-27.490000000000002],[-91.414,-5.158],[-64.068,54.102],[64.069,54.102],[83.437,-17.174]],"v":[[61.182,-35.553],[51.491,-19.065],[46.77,-16.368],[44.004,-17.121],[42.06,-24.609],[51.832,-41.235],[5.469,-54.102],[5.469,-35.221],[-0.001,-29.752],[-5.469,-35.221],[-5.469,-54.102],[-51.829,-41.235],[-42.057,-24.609],[-44.001,-17.121],[-46.768,-16.368],[-51.488,-19.065],[-61.18,-35.554],[-91.414,-5.158],[-64.068,54.102],[64.069,54.102],[91.414,-5.158]],"c":true},"ix":2},"nm":"Path 1","mn":"ADBE Vector Shape - Group","hd":false,"_render":true},{"ty":"fl","c":{"a":0,"k":[0.92,0.92,0.92,1],"ix":4,"x":"var $bm_rt;\ntry {\n    $bm_rt = thisComp.layer('Controller').effect('Color')('ADBE Color Control-0001');\n} catch (e) {\n    $bm_rt = value;\n}"},"o":{"a":0,"k":100,"ix":5},"r":1,"bm":0,"nm":"Fill 1","mn":"ADBE Vector Graphic - Fill","hd":false,"_render":true},{"ty":"tr","p":{"a":0,"k":[91.664,54.352],"ix":2},"a":{"a":0,"k":[0,0],"ix":1},"s":{"a":0,"k":[100,100],"ix":3},"r":{"a":0,"k":0,"ix":6},"o":{"a":0,"k":100,"ix":7},"sk":{"a":0,"k":0,"ix":4},"sa":{"a":0,"k":0,"ix":5},"nm":"Transform","_render":true}],"nm":"Group 1","np":2,"cix":2,"bm":0,"ix":1,"mn":"ADBE Vector Group","hd":false,"_render":true}],"ip":0,"op":150,"st":0,"bm":0,"completed":true},{"ddd":0,"ind":3,"ty":4,"nm":"Arrow","parent":7,"tt":1,"sr":1,"ks":{"o":{"a":0,"k":100,"ix":11},"r":{"a":1,"k":[{"i":{"x":[0.5],"y":[1]},"o":{"x":[0.5],"y":[0]},"t":0,"s":[-29]},{"i":{"x":[0.5],"y":[1]},"o":{"x":[0.5],"y":[0]},"t":22,"s":[40]},{"i":{"x":[0.5],"y":[1]},"o":{"x":[0.5],"y":[0]},"t":28.25,"s":[22]},{"i":{"x":[0.5],"y":[1]},"o":{"x":[0.5],"y":[0]},"t":34.5,"s":[44]},{"i":{"x":[0.5],"y":[1]},"o":{"x":[0.5],"y":[0]},"t":40.75,"s":[22]},{"i":{"x":[0.5],"y":[1]},"o":{"x":[0.5],"y":[0]},"t":47,"s":[40]},{"i":{"x":[0.5],"y":[1]},"o":{"x":[0.5],"y":[0]},"t":70,"s":[-29]},{"i":{"x":[0.5],"y":[1]},"o":{"x":[0.5],"y":[0]},"t":75,"s":[-29]},{"i":{"x":[0.5],"y":[1]},"o":{"x":[0.5],"y":[0]},"t":97,"s":[40]},{"i":{"x":[0.5],"y":[1]},"o":{"x":[0.5],"y":[0]},"t":103.25,"s":[22]},{"i":{"x":[0.5],"y":[1]},"o":{"x":[0.5],"y":[0]},"t":109.5,"s":[44]},{"i":{"x":[0.5],"y":[1]},"o":{"x":[0.5],"y":[0]},"t":115.75,"s":[22]},{"i":{"x":[0.5],"y":[1]},"o":{"x":[0.5],"y":[0]},"t":122,"s":[40]},{"t":145,"s":[-29]}],"ix":10},"p":{"a":0,"k":[175.25,143.375,0],"ix":2},"a":{"a":0,"k":[20.25,56.17,0],"ix":1},"s":{"a":0,"k":[100,100,100],"ix":6}},"ao":0,"shapes":[{"ty":"gr","it":[{"ind":0,"ty":"sh","ix":1,"ks":{"a":0,"k":{"i":[[20,6.612000000000002],[11.046,37.658],[-20,28.704],[0,-37.658]],"o":[[20,28.704],[-11.046,37.658],[-20,6.612000000000002],[0,-37.658]],"v":[[20,17.658],[0,37.658],[-20,17.658],[0,-37.658]],"c":true},"ix":2},"nm":"Path 1","mn":"ADBE Vector Shape - Group","hd":false,"_render":true},{"ty":"fl","c":{"a":0,"k":[0.8118,0.2353,0.2353,1],"ix":4,"x":"var $bm_rt;\ntry {\n    $bm_rt = thisComp.layer('Controller').effect('Color 2')('ADBE Color Control-0001');\n} catch (e) {\n    $bm_rt = value;\n}"},"o":{"a":0,"k":100,"ix":5},"r":1,"bm":0,"nm":"Fill 1","mn":"ADBE Vector Graphic - Fill","hd":false,"_render":true},{"ty":"tr","p":{"a":0,"k":[20.25,37.908],"ix":2},"a":{"a":0,"k":[0,0],"ix":1},"s":{"a":0,"k":[100,100],"ix":3},"r":{"a":0,"k":0,"ix":6},"o":{"a":0,"k":100,"ix":7},"sk":{"a":0,"k":0,"ix":4},"sa":{"a":0,"k":0,"ix":5},"nm":"Transform","_render":true}],"nm":"Group 1","np":2,"cix":2,"bm":0,"ix":1,"mn":"ADBE Vector Group","hd":false,"_render":true}],"ip":0,"op":150,"st":0,"bm":0,"completed":true},{"ddd":0,"ind":4,"ty":4,"nm":"Scoreboard","parent":7,"sr":1,"ks":{"o":{"a":0,"k":100,"ix":11},"r":{"a":0,"k":0,"ix":10},"p":{"a":0,"k":[175.25,88.795,0],"ix":2},"a":{"a":0,"k":[91.664,54.352,0],"ix":1},"s":{"a":0,"k":[100,100,100],"ix":6}},"ao":0,"shapes":[{"ty":"gr","it":[{"ind":0,"ty":"sh","ix":1,"ks":{"a":0,"k":{"i":[[73.132,-27.488999999999997],[51.491,-19.065],[48.645,-16.368],[44.873999999999995,-16.610999999999997],[40.53,-22.005000000000003],[51.832,-41.235],[22.185000000000002,-53.278999999999996],[5.469,-35.221],[3.019,-29.752],[-5.469,-32.199999999999996],[-5.469,-54.102],[-37.908,-48.728],[-42.057,-24.609],[-41.397,-18.654],[-45.828,-16.368],[-50.467999999999996,-17.332],[-61.18,-35.554],[-83.436,-17.174],[-64.068,54.102],[64.069,54.102],[91.414,-5.158]],"o":[[61.182,-35.553],[50.471,-17.332],[45.828,-16.368],[41.4,-18.654],[42.06,-24.609],[37.909,-48.727],[5.469,-54.102],[5.469,-32.199999999999996],[-3.021,-29.752],[-5.469,-35.221],[-22.184,-53.278],[-51.829,-41.235],[-40.527,-22.005000000000003],[-44.870999999999995,-16.610999999999997],[-48.643,-16.368],[-51.488,-19.065],[-73.129,-27.490000000000002],[-91.414,-5.158],[-64.068,54.102],[64.069,54.102],[83.437,-17.174]],"v":[[61.182,-35.553],[51.491,-19.065],[46.77,-16.368],[44.004,-17.121],[42.06,-24.609],[51.832,-41.235],[5.469,-54.102],[5.469,-35.221],[-0.001,-29.752],[-5.469,-35.221],[-5.469,-54.102],[-51.829,-41.235],[-42.057,-24.609],[-44.001,-17.121],[-46.768,-16.368],[-51.488,-19.065],[-61.18,-35.554],[-91.414,-5.158],[-64.068,54.102],[64.069,54.102],[91.414,-5.158]],"c":true},"ix":2},"nm":"Path 1","mn":"ADBE Vector Shape - Group","hd":false,"_render":true},{"ty":"fl","c":{"a":0,"k":[0.92,0.92,0.92,1],"ix":4,"x":"var $bm_rt;\ntry {\n    $bm_rt = thisComp.layer('Controller')('Effects')('Color')('ADBE Color Control-0001');\n} catch (e) {\n    $bm_rt = value;\n}"},"o":{"a":0,"k":100,"ix":5},"r":1,"bm":0,"nm":"Fill 1","mn":"ADBE Vector Graphic - Fill","hd":false,"_render":true},{"ty":"tr","p":{"a":0,"k":[91.664,54.352],"ix":2},"a":{"a":0,"k":[0,0],"ix":1},"s":{"a":0,"k":[100,100],"ix":3},"r":{"a":0,"k":0,"ix":6},"o":{"a":0,"k":100,"ix":7},"sk":{"a":0,"k":0,"ix":4},"sa":{"a":0,"k":0,"ix":5},"nm":"Transform","_render":true}],"nm":"Group 1","np":2,"cix":2,"bm":0,"ix":1,"mn":"ADBE Vector Group","hd":false,"_render":true}],"ip":0,"op":150,"st":0,"bm":0,"completed":true},{"ddd":0,"ind":5,"ty":4,"nm":"Place 1","parent":7,"sr":1,"ks":{"o":{"a":0,"k":100,"ix":11},"r":{"a":0,"k":0,"ix":10},"p":{"a":0,"k":[97.388,231.337,0],"ix":2},"a":{"a":0,"k":[56.235,83.221,0],"ix":1},"s":{"a":1,"k":[{"i":{"x":[0.5,0.5,0.5],"y":[1,1,1]},"o":{"x":[0.5,0.5,0.5],"y":[0,0,0]},"t":0,"s":[100,100,100]},{"i":{"x":[0.5,0.5,0.5],"y":[1,1,1]},"o":{"x":[0.5,0.5,0.5],"y":[0,0,0]},"t":10,"s":[92,92,100]},{"i":{"x":[0.5,0.5,0.5],"y":[1,1,1]},"o":{"x":[0.5,0.5,0.5],"y":[0,0,0]},"t":59,"s":[92,92,100]},{"i":{"x":[0.5,0.5,0.5],"y":[1,1,1]},"o":{"x":[0.5,0.5,0.5],"y":[0,0,0]},"t":70,"s":[100,100,100]},{"i":{"x":[0.5,0.5,0.5],"y":[1,1,1]},"o":{"x":[0.5,0.5,0.5],"y":[0,0,0]},"t":75,"s":[100,100,100]},{"i":{"x":[0.5,0.5,0.5],"y":[1,1,1]},"o":{"x":[0.5,0.5,0.5],"y":[0,0,0]},"t":85,"s":[92,92,100]},{"i":{"x":[0.5,0.5,0.5],"y":[1,1,1]},"o":{"x":[0.5,0.5,0.5],"y":[0,0,0]},"t":134,"s":[92,92,100]},{"t":145,"s":[100,100,100]}],"ix":6}},"ao":0,"shapes":[{"ty":"gr","it":[{"ind":0,"ty":"sh","ix":1,"ks":{"a":0,"k":{"i":[[20.122,-50.618],[-8.56,-61.696999999999996],[-16.021,-82.971],[-47.479,-82.971],[-55.985,-79.16300000000001],[-55.985,74.465],[-52.177,82.971],[47.479,82.971],[55.985,79.162],[55.985,-42.112],[52.177,-50.618]],"o":[[4.475,-50.618],[-12.368,-80.331],[-19.986,-82.971],[-52.177,-82.971],[-55.985,-74.465],[-55.985,79.162],[-47.479,82.971],[52.177,82.971],[55.985,74.465],[55.985,-46.81],[47.479,-50.618]],"v":[[20.122,-50.618],[-11.574,-76.446],[-19.986,-82.971],[-47.479,-82.971],[-55.985,-74.465],[-55.985,74.465],[-47.479,82.971],[47.479,82.971],[55.985,74.465],[55.985,-42.112],[47.479,-50.618]],"c":true},"ix":2},"nm":"Path 1","mn":"ADBE Vector Shape - Group","hd":false,"_render":true},{"ty":"fl","c":{"a":0,"k":[0.7286,0.3514,0.3514,1],"ix":4,"x":"var $bm_rt;\ntry {\n    $bm_rt = thisComp.layer('Controller').effect('Color 3')('ADBE Color Control-0001');\n} catch (e) {\n    $bm_rt = value;\n}"},"o":{"a":0,"k":100,"ix":5},"r":1,"bm":0,"nm":"Fill 1","mn":"ADBE Vector Graphic - Fill","hd":false,"_render":true},{"ty":"tr","p":{"a":0,"k":[56.235,83.221],"ix":2},"a":{"a":0,"k":[0,0],"ix":1},"s":{"a":0,"k":[100,100],"ix":3},"r":{"a":0,"k":0,"ix":6},"o":{"a":0,"k":100,"ix":7},"sk":{"a":0,"k":0,"ix":4},"sa":{"a":0,"k":0,"ix":5},"nm":"Transform","_render":true}],"nm":"Group 1","np":2,"cix":2,"bm":0,"ix":1,"mn":"ADBE Vector Group","hd":false,"_render":true}],"ip":0,"op":150,"st":0,"bm":0,"completed":true},{"ddd":0,"ind":6,"ty":4,"nm":"Place 2","parent":7,"sr":1,"ks":{"o":{"a":0,"k":100,"ix":11},"r":{"a":0,"k":0,"ix":10},"p":{"a":0,"k":[253.113,231.337,0],"ix":2},"a":{"a":0,"k":[56.235,83.221,0],"ix":1},"s":{"a":1,"k":[{"i":{"x":[0.5,0.5,0.5],"y":[1,1,1]},"o":{"x":[0.5,0.5,0.5],"y":[0,0,0]},"t":10,"s":[100,100,100]},{"i":{"x":[0.5,0.5,0.5],"y":[1,1,1]},"o":{"x":[0.5,0.5,0.5],"y":[0,0,0]},"t":22,"s":[92,92,100]},{"i":{"x":[0.5,0.5,0.5],"y":[1,1,1]},"o":{"x":[0.5,0.5,0.5],"y":[0,0,0]},"t":47,"s":[92,92,100]},{"i":{"x":[0.5,0.5,0.5],"y":[1,1,1]},"o":{"x":[0.5,0.5,0.5],"y":[0,0,0]},"t":59,"s":[100,100,100]},{"i":{"x":[0.5,0.5,0.5],"y":[1,1,1]},"o":{"x":[0.5,0.5,0.5],"y":[0,0,0]},"t":85,"s":[100,100,100]},{"i":{"x":[0.5,0.5,0.5],"y":[1,1,1]},"o":{"x":[0.5,0.5,0.5],"y":[0,0,0]},"t":97,"s":[92,92,100]},{"i":{"x":[0.5,0.5,0.5],"y":[1,1,1]},"o":{"x":[0.5,0.5,0.5],"y":[0,0,0]},"t":122,"s":[92,92,100]},{"t":134,"s":[100,100,100]}],"ix":6}},"ao":0,"shapes":[{"ty":"gr","it":[{"ind":0,"ty":"sh","ix":1,"ks":{"a":0,"k":{"i":[[-20.122,-50.618],[8.56,-61.696999999999996],[16.021,-82.971],[47.479,-82.971],[55.985,-79.16300000000001],[55.985,74.465],[52.177,82.971],[-47.479,82.971],[-55.985,79.162],[-55.985,-42.112],[-52.177,-50.618]],"o":[[-4.475,-50.618],[12.368,-80.331],[19.986,-82.971],[52.177,-82.971],[55.985,-74.465],[55.985,79.162],[47.479,82.971],[-52.177,82.971],[-55.985,74.465],[-55.985,-46.81],[-47.479,-50.618]],"v":[[-20.122,-50.618],[11.574,-76.446],[19.986,-82.971],[47.479,-82.971],[55.985,-74.465],[55.985,74.465],[47.479,82.971],[-47.479,82.971],[-55.985,74.465],[-55.985,-42.112],[-47.479,-50.618]],"c":true},"ix":2},"nm":"Path 1","mn":"ADBE Vector Shape - Group","hd":false,"_render":true},{"ty":"fl","c":{"a":0,"k":[0.7286,0.3514,0.3514,1],"ix":4,"x":"var $bm_rt;\ntry {\n    $bm_rt = thisComp.layer('Controller')('Effects')('Color 3')('ADBE Color Control-0001');\n} catch (e) {\n    $bm_rt = value;\n}"},"o":{"a":0,"k":100,"ix":5},"r":1,"bm":0,"nm":"Fill 1","mn":"ADBE Vector Graphic - Fill","hd":false,"_render":true},{"ty":"tr","p":{"a":0,"k":[56.235,83.221],"ix":2},"a":{"a":0,"k":[0,0],"ix":1},"s":{"a":0,"k":[100,100],"ix":3},"r":{"a":0,"k":0,"ix":6},"o":{"a":0,"k":100,"ix":7},"sk":{"a":0,"k":0,"ix":4},"sa":{"a":0,"k":0,"ix":5},"nm":"Transform","_render":true}],"nm":"Group 1","np":2,"cix":2,"bm":0,"ix":1,"mn":"ADBE Vector Group","hd":false,"_render":true}],"ip":0,"op":150,"st":0,"bm":0,"completed":true},{"ddd":0,"ind":7,"ty":4,"nm":"Main","sr":1,"ks":{"o":{"a":0,"k":100,"ix":11},"r":{"a":0,"k":0,"ix":10},"p":{"a":0,"k":[250,250,0],"ix":2},"a":{"a":0,"k":[175.25,175.25,0],"ix":1},"s":{"a":1,"k":[{"i":{"x":[0.5,0.5,0.5],"y":[1,1,1]},"o":{"x":[0.5,0.5,0.5],"y":[0,0,0]},"t":0,"s":[100,100,100]},{"i":{"x":[0.5,0.5,0.5],"y":[1,1,1]},"o":{"x":[0.5,0.5,0.5],"y":[0,0,0]},"t":22,"s":[92,92,100]},{"i":{"x":[0.5,0.5,0.5],"y":[1,1,1]},"o":{"x":[0.5,0.5,0.5],"y":[0,0,0]},"t":47,"s":[92,92,100]},{"i":{"x":[0.5,0.5,0.5],"y":[1,1,1]},"o":{"x":[0.5,0.5,0.5],"y":[0,0,0]},"t":70,"s":[100,100,100]},{"i":{"x":[0.5,0.5,0.5],"y":[1,1,1]},"o":{"x":[0.5,0.5,0.5],"y":[0,0,0]},"t":75,"s":[100,100,100]},{"i":{"x":[0.5,0.5,0.5],"y":[1,1,1]},"o":{"x":[0.5,0.5,0.5],"y":[0,0,0]},"t":97,"s":[92,92,100]},{"i":{"x":[0.5,0.5,0.5],"y":[1,1,1]},"o":{"x":[0.5,0.5,0.5],"y":[0,0,0]},"t":122,"s":[92,92,100]},{"t":145,"s":[100,100,100]}],"ix":6}},"ao":0,"shapes":[{"ty":"gr","it":[{"ind":0,"ty":"sh","ix":1,"ks":{"a":0,"k":{"i":[[165.36900000000003,-133.981],[99.116,-133.981],[38.711,-175],[-73.69999999999999,-159.298],[-153.597,-133.981],[-175,-124.35],[-175,153.597],[-165.369,175],[153.598,175],[175,165.369],[175,-112.579]],"o":[[153.598,-133.981],[73.701,-159.298],[-38.71,-175],[-99.115,-133.981],[-165.369,-133.981],[-175,-112.579],[-175,165.369],[-153.597,175],[165.36900000000003,175],[175,153.597],[175,-124.35]],"v":[[153.598,-133.981],[99.116,-133.981],[0,-175],[-99.115,-133.981],[-153.597,-133.981],[-175,-112.579],[-175,153.597],[-153.597,175],[153.598,175],[175,153.597],[175,-112.579]],"c":true},"ix":2},"nm":"Path 1","mn":"ADBE Vector Shape - Group","hd":false,"_render":true},{"ty":"fl","c":{"a":0,"k":[0.8729,0.5071,0.5071,1],"ix":4,"x":"var $bm_rt;\ntry {\n    $bm_rt = thisComp.layer('Controller').effect('Color 4')('ADBE Color Control-0001');\n} catch (e) {\n    $bm_rt = value;\n}"},"o":{"a":0,"k":100,"ix":5},"r":1,"bm":0,"nm":"Fill 1","mn":"ADBE Vector Graphic - Fill","hd":false,"_render":true},{"ty":"tr","p":{"a":0,"k":[175.25,175.25],"ix":2},"a":{"a":0,"k":[0,0],"ix":1},"s":{"a":0,"k":[100,100],"ix":3},"r":{"a":0,"k":0,"ix":6},"o":{"a":0,"k":100,"ix":7},"sk":{"a":0,"k":0,"ix":4},"sa":{"a":0,"k":0,"ix":5},"nm":"Transform","_render":true}],"nm":"Group 1","np":2,"cix":2,"bm":0,"ix":1,"mn":"ADBE Vector Group","hd":false,"_render":true}],"ip":0,"op":150,"st":0,"bm":0,"completed":true}],"markers":[],"__complete":true}